{
  "id": "primegov-louisvilleky-10182",
  "body_id": "limerick-architectural-review-committee",
  "title": "Limerick Architectural Review Committee",
  "date": "2026-02-18",
  "time": "16:30",
  "source_type": "primegov",
  "source_url": "https://louisvilleky.primegov.com/public/Portal/Meeting?meetingTemplateId=10182",
  "source_meeting_id": "10182",
  "video_url": "https://louisvilleky.new.swagit.com/events/45009",
  "attachments": [
    {
      "sha256": "759b50f35b10621029548414a5a2f474b5db997944f3e01219a5b87c98a6f228",
      "url": "https://pgwest.blob.core.windows.net/louisvilleky/Meetings/10182/Agenda_20260213213039723.pdf?sv=2017-04-17&sr=b&sig=UKSEhMTpA3KAzurFrp%2B%2F1tvl5RKaihuUTnvrFJinHeY%3D&st=2026-05-02T05%3A46%3A56Z&se=2026-05-04T05%3A46%3A56Z&sp=r",
      "mime": "application/pdf",
      "template_name": "Agenda",
      "extracted_text_path": "data/attachments/759b50f35b10621029548414a5a2f474b5db997944f3e01219a5b87c98a6f228.txt"
    }
  ],
  "items": []
}