{
  "id": "openstates-ky-2026RS-hb228",
  "body_ids": [
    "ky-house"
  ],
  "session": "2026RS",
  "identifier": "HB 228",
  "title": "AN ACT relating to a tax credit for renters.",
  "abstract": "Create a new section of KRS Chapter 141 to establish a refundable qualified rent payment credit for taxable years beginning on or after January 1, 2027, but before January 1, 2031, in the amount of 25% of the qualified rent payments made during the taxable year, not to exceed $1,000; amend KRS 141.0205 to order the credit; amend KRS 131.190 to allow reporting by the Department of Revenue.",
  "classification": [
    "bill"
  ],
  "sponsors": [
    {
      "name": "J. Watkins",
      "party": null,
      "district": "42",
      "primary": true
    },
    {
      "name": "C. Aull",
      "party": null,
      "district": "79",
      "primary": true
    },
    {
      "name": "T. Bojanowski",
      "party": null,
      "district": "32",
      "primary": true
    },
    {
      "name": "G. Brown Jr.",
      "party": null,
      "district": "77",
      "primary": true
    },
    {
      "name": "A. Camuel",
      "party": null,
      "district": "93",
      "primary": true
    },
    {
      "name": "B. Chester-Burton",
      "party": null,
      "district": "44",
      "primary": true
    },
    {
      "name": "A. Donworth",
      "party": null,
      "district": "76",
      "primary": true
    },
    {
      "name": "A. Gentry",
      "party": null,
      "district": "46",
      "primary": true
    },
    {
      "name": "M. Lehman",
      "party": null,
      "district": "67",
      "primary": true
    },
    {
      "name": "M. Marzian",
      "party": null,
      "district": "41",
      "primary": true
    },
    {
      "name": "S. Stalker",
      "party": null,
      "district": "34",
      "primary": true
    },
    {
      "name": "P. Stevenson",
      "party": null,
      "district": "43",
      "primary": true
    },
    {
      "name": "L. Willner",
      "party": null,
      "district": "35",
      "primary": true
    }
  ],
  "actions": [
    {
      "date": "2026-01-07",
      "description": "introduced in House",
      "chamber": "lower",
      "classification": [
        "introduction"
      ]
    },
    {
      "date": "2026-01-07",
      "description": "to Committee on Committees (H)",
      "chamber": "lower",
      "classification": [
        "referral-committee"
      ]
    },
    {
      "date": "2026-01-14",
      "description": "to Appropriations & Revenue (H)",
      "chamber": "lower",
      "classification": [
        "referral-committee"
      ]
    }
  ],
  "votes": [],
  "subjects": [
    "Landlord And Tenant",
    "Reports Mandated",
    "Taxation",
    "Taxation, Income--Individual"
  ],
  "chamber_progress": {
    "lower": "in_committee",
    "upper": null,
    "governor": null
  },
  "current_status": "In House committee",
  "last_action_date": "2026-01-14",
  "source_url": "",
  "openstates_id": "ocd-bill/0cc898d8-9c16-438b-a795-74f9643f7562"
}