{
  "id": "openstates-ky-2026RS-hb249",
  "body_ids": [
    "ky-house",
    "ky-senate"
  ],
  "session": "2026RS",
  "identifier": "HB 249",
  "title": "AN ACT relating to involuntary commitment.",
  "abstract": "Amend KRS 202C.010 to include a violation of sexual abuse in the first degree to the definition of \"qualifying offense\"; make technical corrections.",
  "classification": [
    "bill"
  ],
  "sponsors": [
    {
      "name": "M. Whitaker",
      "party": null,
      "district": "94",
      "primary": true
    },
    {
      "name": "B. Chester-Burton",
      "party": null,
      "district": "44",
      "primary": true
    },
    {
      "name": "D. Grossberg",
      "party": null,
      "district": "30",
      "primary": true
    },
    {
      "name": "B. Wesley",
      "party": null,
      "district": "91",
      "primary": true
    }
  ],
  "actions": [
    {
      "date": "2026-01-08",
      "description": "introduced in House",
      "chamber": "lower",
      "classification": [
        "introduction"
      ]
    },
    {
      "date": "2026-01-08",
      "description": "to Committee on Committees (H)",
      "chamber": "lower",
      "classification": [
        "referral-committee"
      ]
    },
    {
      "date": "2026-01-15",
      "description": "to Judiciary (H)",
      "chamber": "lower",
      "classification": [
        "referral-committee"
      ]
    },
    {
      "date": "2026-02-04",
      "description": "reported favorably, 1st reading, to Calendar",
      "chamber": "lower",
      "classification": [
        "committee-passage"
      ]
    },
    {
      "date": "2026-02-05",
      "description": "2nd reading, to Rules",
      "chamber": "lower",
      "classification": [
        "reading-2"
      ]
    },
    {
      "date": "2026-02-19",
      "description": "floor amendment (1) filed",
      "chamber": "lower",
      "classification": [
        "amendment-introduction"
      ]
    },
    {
      "date": "2026-02-20",
      "description": "posted for passage in the Regular Orders of the Day for Monday, February 23 2026",
      "chamber": "lower",
      "classification": []
    },
    {
      "date": "2026-02-23",
      "description": "3rd reading, passed 94-0 with Floor Amendment (1)",
      "chamber": "lower",
      "classification": [
        "passage",
        "reading-3"
      ]
    },
    {
      "date": "2026-02-24",
      "description": "received in Senate",
      "chamber": "upper",
      "classification": []
    },
    {
      "date": "2026-02-24",
      "description": "to Committee on Committees (S)",
      "chamber": "upper",
      "classification": [
        "referral-committee"
      ]
    }
  ],
  "votes": [
    {
      "motion": "Pass",
      "date": "2026-02-23",
      "chamber": "lower",
      "result": "pass",
      "counts": {
        "yes": 94,
        "no": 0,
        "abstain": 0,
        "not voting": 0
      },
      "member_votes": [
        {
          "name": "Aull",
          "option": "yes"
        },
        {
          "name": "Decker",
          "option": "yes"
        },
        {
          "name": "Hampton",
          "option": "yes"
        },
        {
          "name": "Marzian",
          "option": "yes"
        },
        {
          "name": "Roarx",
          "option": "yes"
        },
        {
          "name": "Baker",
          "option": "yes"
        },
        {
          "name": "Dietz",
          "option": "yes"
        },
        {
          "name": "Hancock",
          "option": "yes"
        },
        {
          "name": "Massaroni",
          "option": "yes"
        },
        {
          "name": "Roberts",
          "option": "yes"
        },
        {
          "name": "Banta",
          "option": "yes"
        },
        {
          "name": "Doan",
          "option": "yes"
        },
        {
          "name": "Hart",
          "option": "yes"
        },
        {
          "name": "McCool",
          "option": "yes"
        },
        {
          "name": "Rudy",
          "option": "yes"
        },
        {
          "name": "Bauman",
          "option": "yes"
        },
        {
          "name": "Donworth",
          "option": "yes"
        },
        {
          "name": "Heavrin",
          "option": "yes"
        },
        {
          "name": "McPherson",
          "option": "yes"
        },
        {
          "name": "Sharp",
          "option": "yes"
        },
        {
          "name": "Bivens",
          "option": "yes"
        },
        {
          "name": "Dossett",
          "option": "yes"
        },
        {
          "name": "Hodgson",
          "option": "yes"
        },
        {
          "name": "Meade",
          "option": "yes"
        },
        {
          "name": "Smith",
          "option": "yes"
        },
        {
          "name": "Blanton",
          "option": "yes"
        },
        {
          "name": "Dotson",
          "option": "yes"
        },
        {
          "name": "Holloway",
          "option": "yes"
        },
        {
          "name": "Meredith",
          "option": "yes"
        },
        {
          "name": "Stalker",
          "option": "yes"
        },
        {
          "name": "Bojanowski",
          "option": "yes"
        },
        {
          "name": "Duvall",
          "option": "yes"
        },
        {
          "name": "Huff T",
          "option": "yes"
        },
        {
          "name": "Miles",
          "option": "yes"
        },
        {
          "name": "Stevenson P",
          "option": "yes"
        },
        {
          "name": "Bowling",
          "option": "yes"
        },
        {
          "name": "Elliott",
          "option": "yes"
        },
        {
          "name": "Imes",
          "option": "yes"
        },
        {
          "name": "Moore",
          "option": "yes"
        },
        {
          "name": "Tate",
          "option": "yes"
        },
        {
          "name": "Branscum",
          "option": "yes"
        },
        {
          "name": "Fister",
          "option": "yes"
        },
        {
          "name": "Jackson",
          "option": "yes"
        },
        {
          "name": "Moser",
          "option": "yes"
        },
        {
          "name": "Thomas",
          "option": "yes"
        },
        {
          "name": "Bratcher S.",
          "option": "yes"
        },
        {
          "name": "Flannery",
          "option": "yes"
        },
        {
          "name": "Johnson",
          "option": "yes"
        },
        {
          "name": "Neighbors",
          "option": "yes"
        },
        {
          "name": "Thompson",
          "option": "yes"
        },
        {
          "name": "Bray",
          "option": "yes"
        },
        {
          "name": "Fleming",
          "option": "yes"
        },
        {
          "name": "King",
          "option": "yes"
        },
        {
          "name": "Nemes",
          "option": "yes"
        },
        {
          "name": "Tipton",
          "option": "yes"
        },
        {
          "name": "Bridges",
          "option": "yes"
        },
        {
          "name": "Fugate",
          "option": "yes"
        },
        {
          "name": "Koch",
          "option": "yes"
        },
        {
          "name": "Osborne",
          "option": "yes"
        },
        {
          "name": "Upchurch",
          "option": "yes"
        },
        {
          "name": "Brown",
          "option": "yes"
        },
        {
          "name": "Gentry",
          "option": "yes"
        },
        {
          "name": "Kulkarni",
          "option": "yes"
        },
        {
          "name": "Payne",
          "option": "yes"
        },
        {
          "name": "Watkins",
          "option": "yes"
        },
        {
          "name": "Burke",
          "option": "yes"
        },
        {
          "name": "Gooch",
          "option": "yes"
        },
        {
          "name": "Lehman",
          "option": "yes"
        },
        {
          "name": "Petrie",
          "option": "yes"
        },
        {
          "name": "Wesley",
          "option": "yes"
        },
        {
          "name": "Callaway",
          "option": "yes"
        },
        {
          "name": "Gordon",
          "option": "yes"
        },
        {
          "name": "Lewis C",
          "option": "yes"
        },
        {
          "name": "Pollock",
          "option": "yes"
        },
        {
          "name": "Whitaker",
          "option": "yes"
        },
        {
          "name": "Calloway",
          "option": "yes"
        },
        {
          "name": "Griffee",
          "option": "yes"
        },
        {
          "name": "Lewis D",
          "option": "yes"
        },
        {
          "name": "Proctor",
          "option": "yes"
        },
        {
          "name": "Williams",
          "option": "yes"
        },
        {
          "name": "Camuel",
          "option": "yes"
        },
        {
          "name": "Grossberg",
          "option": "yes"
        },
        {
          "name": "Lewis S",
          "option": "yes"
        },
        {
          "name": "Rabourn",
          "option": "yes"
        },
        {
          "name": "Willner",
          "option": "yes"
        },
        {
          "name": "Chester-Burton",
          "option": "yes"
        },
        {
          "name": "Grossl",
          "option": "yes"
        },
        {
          "name": "Lockett",
          "option": "yes"
        },
        {
          "name": "Raymer",
          "option": "yes"
        },
        {
          "name": "Witten",
          "option": "yes"
        },
        {
          "name": "Clines",
          "option": "yes"
        },
        {
          "name": "Hale",
          "option": "yes"
        },
        {
          "name": "Maddox",
          "option": "yes"
        },
        {
          "name": "Riley",
          "option": "yes"
        },
        {
          "name": "Freeland",
          "option": "not voting"
        },
        {
          "name": "Tackett Laferty",
          "option": "not voting"
        },
        {
          "name": "Truett",
          "option": "not voting"
        },
        {
          "name": "White",
          "option": "not voting"
        },
        {
          "name": "Wilson",
          "option": "not voting"
        },
        {
          "name": "Lawrence",
          "option": "not voting"
        }
      ]
    }
  ],
  "subjects": [
    "Civil Procedure",
    "Corrections Impact",
    "Courts",
    "Courts, Circuit",
    "Criminal Procedure",
    "Local Mandate",
    "Mental Health"
  ],
  "chamber_progress": {
    "lower": "passed",
    "upper": "in_committee",
    "governor": null
  },
  "current_status": "Passed House, in Senate committee",
  "last_action_date": "2026-02-24",
  "source_url": "",
  "openstates_id": "ocd-bill/f3585b5d-b9b4-4e3b-9a1b-698b6e67eba7"
}