{
  "id": "openstates-ky-2026RS-hb331",
  "body_ids": [
    "ky-house"
  ],
  "session": "2026RS",
  "identifier": "HB 331",
  "title": "AN ACT relating to real property purchased at a master commissioner's sale.",
  "abstract": "Amend KRS 91.514 and create a new section of KRS Chapter 426 to establish that any residential property that is purchased at a master commissioner's sale or other court-ordered sale in a county that has a land bank authority and was occupied at any time within the 2 years prior to the sale must undergo renovations within 6 months of obtaining the title to the property and must be returned to a state of occupancy within specified time periods; define terms; establish a fine of $100 per day payable to the local government for noncompliance.",
  "classification": [
    "bill"
  ],
  "sponsors": [
    {
      "name": "D. Grossberg",
      "party": null,
      "district": "30",
      "primary": true
    }
  ],
  "actions": [
    {
      "date": "2026-01-12",
      "description": "introduced in House",
      "chamber": "lower",
      "classification": [
        "introduction"
      ]
    },
    {
      "date": "2026-01-12",
      "description": "to Committee on Committees (H)",
      "chamber": "lower",
      "classification": [
        "referral-committee"
      ]
    },
    {
      "date": "2026-01-20",
      "description": "to Judiciary (H)",
      "chamber": "lower",
      "classification": [
        "referral-committee"
      ]
    }
  ],
  "votes": [],
  "subjects": [
    "Cities",
    "Consolidated Local Governments",
    "Counties",
    "Counties, Charter",
    "Counties, Urban",
    "Courts",
    "Local Mandate",
    "Property",
    "Real Estate",
    "Unified Local Governments"
  ],
  "chamber_progress": {
    "lower": "in_committee",
    "upper": null,
    "governor": null
  },
  "current_status": "In House committee",
  "last_action_date": "2026-01-20",
  "source_url": "",
  "openstates_id": "ocd-bill/3309c58b-da66-4432-8d97-59c7a8c09d36"
}