{
  "id": "openstates-ky-2026RS-hb394",
  "body_ids": [
    "ky-house"
  ],
  "session": "2026RS",
  "identifier": "HB 394",
  "title": "AN ACT relating to prohibited uses of tax dollars.",
  "abstract": "Amend KRS 65.013 to create a cause of action for violations of the use of tax dollars to advocate for or against public questions on the ballot or to lobby or participate in executive agency lobbying; establish time limitation to commence suit and appropriate venue; provide damages recoverable per violation; allow for a class action; prohibit persons held civilly liable from holding a position of public trust or profit for 10 years; create a new section of KRS Chapter 65 to establish a criminal penalty and a prohibition against holding a position of public trust or profit for 10 years for individuals found guilty of a violation.",
  "classification": [
    "bill"
  ],
  "sponsors": [
    {
      "name": "F. Rabourn",
      "party": null,
      "district": "47",
      "primary": true
    },
    {
      "name": "T. Roberts",
      "party": null,
      "district": "66",
      "primary": true
    },
    {
      "name": "S. Baker",
      "party": null,
      "district": "85",
      "primary": true
    },
    {
      "name": "J. Calloway",
      "party": null,
      "district": "10",
      "primary": true
    },
    {
      "name": "S. Doan",
      "party": null,
      "district": "69",
      "primary": true
    },
    {
      "name": "V. Grossl",
      "party": null,
      "district": "88",
      "primary": true
    },
    {
      "name": "M. Hart",
      "party": null,
      "district": "78",
      "primary": true
    },
    {
      "name": "K. Holloway",
      "party": null,
      "district": "2",
      "primary": true
    },
    {
      "name": "T. Huff",
      "party": null,
      "district": "49",
      "primary": true
    },
    {
      "name": "S. Maddox",
      "party": null,
      "district": "61",
      "primary": true
    },
    {
      "name": "C. Massaroni",
      "party": null,
      "district": "50",
      "primary": true
    },
    {
      "name": "M. Proctor",
      "party": null,
      "district": "60",
      "primary": true
    }
  ],
  "actions": [
    {
      "date": "2026-01-15",
      "description": "introduced in House",
      "chamber": "lower",
      "classification": [
        "introduction"
      ]
    },
    {
      "date": "2026-01-15",
      "description": "to Committee on Committees (H)",
      "chamber": "lower",
      "classification": [
        "referral-committee"
      ]
    },
    {
      "date": "2026-01-23",
      "description": "to Elections, Const. Amendments & Intergovernmental Affairs (H)",
      "chamber": "lower",
      "classification": [
        "referral-committee"
      ]
    }
  ],
  "votes": [],
  "subjects": [
    "Civil Actions",
    "Claims",
    "Crimes And Punishments",
    "Elections And Voting",
    "Public Officers And Employees",
    "State Agencies"
  ],
  "chamber_progress": {
    "lower": "in_committee",
    "upper": null,
    "governor": null
  },
  "current_status": "In House committee",
  "last_action_date": "2026-01-23",
  "source_url": "",
  "openstates_id": "ocd-bill/6ebf2ce5-ef15-42ac-91a3-2b08bb2e670d"
}