{
  "id": "openstates-ky-2026RS-hb481",
  "body_ids": [
    "ky-house"
  ],
  "session": "2026RS",
  "identifier": "HB 481",
  "title": "AN ACT relating to sex offenders.",
  "abstract": "Amend KRS 17.545 to prohibit a registrant from residing within 3,000 feet of a high school, middle school, elementary school, preschool, publicly owned or leased playground, or licensed day care facility; provide that the 3,000 feet restriction applies to any person who becomes a registrant after the effective date of the Act.",
  "classification": [
    "bill"
  ],
  "sponsors": [
    {
      "name": "F. Rabourn",
      "party": null,
      "district": "47",
      "primary": true
    },
    {
      "name": "C. Massaroni",
      "party": null,
      "district": "50",
      "primary": true
    },
    {
      "name": "T. Roberts",
      "party": null,
      "district": "66",
      "primary": true
    }
  ],
  "actions": [
    {
      "date": "2026-01-23",
      "description": "introduced in House",
      "chamber": "lower",
      "classification": [
        "introduction"
      ]
    },
    {
      "date": "2026-01-23",
      "description": "to Committee on Committees (H)",
      "chamber": "lower",
      "classification": [
        "referral-committee"
      ]
    },
    {
      "date": "2026-02-02",
      "description": "to Judiciary (H)",
      "chamber": "lower",
      "classification": [
        "referral-committee"
      ]
    }
  ],
  "votes": [],
  "subjects": [
    "Children And Minors",
    "Corrections Impact",
    "Crimes And Punishments",
    "Criminal Procedure",
    "Education, Elementary And Secondary",
    "Local Mandate",
    "Parks And Shrines",
    "Public Safety"
  ],
  "chamber_progress": {
    "lower": "in_committee",
    "upper": null,
    "governor": null
  },
  "current_status": "In House committee",
  "last_action_date": "2026-02-02",
  "source_url": "",
  "openstates_id": "ocd-bill/b92c9378-62b8-40c5-b434-6e0cf7571a0d"
}