{
  "id": "openstates-ky-2026RS-hb583",
  "body_ids": [
    "ky-house",
    "ky-senate"
  ],
  "session": "2026RS",
  "identifier": "HB 583",
  "title": "AN ACT relating to the school-based Medicaid program.",
  "abstract": "Create a new section of KRS Chapter 160 to require school districts that elect to provide health care services through a school nurse to bill the school-based Medicaid program for medically necessary services provided to a student enrolled in Medicaid; establish requirements for third-party Medicaid billing vendors contracted by school districts; permit school nurses to receive preventative dental services training from the Department for Public Health; permit the school district to bill the school-based Medicaid program for preventative dental services that are within a school nurse's scope of practice.",
  "classification": [
    "bill"
  ],
  "sponsors": [
    {
      "name": "S. Riley",
      "party": null,
      "district": "23",
      "primary": true
    },
    {
      "name": "R. Duvall",
      "party": null,
      "district": "17",
      "primary": true
    },
    {
      "name": "P. Flannery",
      "party": null,
      "district": "96",
      "primary": true
    },
    {
      "name": "V. Grossl",
      "party": null,
      "district": "88",
      "primary": true
    },
    {
      "name": "K. Jackson",
      "party": null,
      "district": "20",
      "primary": true
    },
    {
      "name": "S. Lewis",
      "party": null,
      "district": "14",
      "primary": true
    },
    {
      "name": "S. McPherson",
      "party": null,
      "district": "22",
      "primary": true
    },
    {
      "name": "J. Payne",
      "party": null,
      "district": "11",
      "primary": true
    },
    {
      "name": "N. Tate",
      "party": null,
      "district": "27",
      "primary": true
    },
    {
      "name": "W. Thomas",
      "party": null,
      "district": "8",
      "primary": true
    },
    {
      "name": "L. Willner",
      "party": null,
      "district": "35",
      "primary": true
    }
  ],
  "actions": [
    {
      "date": "2026-02-06",
      "description": "introduced in House",
      "chamber": "lower",
      "classification": [
        "introduction"
      ]
    },
    {
      "date": "2026-02-06",
      "description": "to Committee on Committees (H)",
      "chamber": "lower",
      "classification": [
        "referral-committee"
      ]
    },
    {
      "date": "2026-02-13",
      "description": "to Health Services (H)",
      "chamber": "lower",
      "classification": [
        "referral-committee"
      ]
    },
    {
      "date": "2026-03-12",
      "description": "reported favorably, 1st reading, to Calendar",
      "chamber": "lower",
      "classification": [
        "committee-passage"
      ]
    },
    {
      "date": "2026-03-13",
      "description": "2nd reading, to Rules",
      "chamber": "lower",
      "classification": [
        "reading-2"
      ]
    },
    {
      "date": "2026-03-19",
      "description": "floor amendment (1) filed",
      "chamber": "lower",
      "classification": [
        "amendment-introduction"
      ]
    },
    {
      "date": "2026-03-20",
      "description": "posted for passage in the Regular Orders of the Day for Tuesday, March 24 2026",
      "chamber": "lower",
      "classification": []
    },
    {
      "date": "2026-03-24",
      "description": "3rd reading, passed 86-0 with Floor Amendment (1)",
      "chamber": "lower",
      "classification": [
        "passage",
        "reading-3"
      ]
    },
    {
      "date": "2026-03-25",
      "description": "received in Senate",
      "chamber": "upper",
      "classification": []
    },
    {
      "date": "2026-03-25",
      "description": "to Committee on Committees (S)",
      "chamber": "upper",
      "classification": [
        "referral-committee"
      ]
    }
  ],
  "votes": [
    {
      "motion": "Pass",
      "date": "2026-03-24",
      "chamber": "lower",
      "result": "pass",
      "counts": {
        "yes": 86,
        "no": 0,
        "abstain": 0,
        "not voting": 0
      },
      "member_votes": [
        {
          "name": "Aull",
          "option": "yes"
        },
        {
          "name": "Donworth",
          "option": "yes"
        },
        {
          "name": "Hancock",
          "option": "yes"
        },
        {
          "name": "McCool",
          "option": "yes"
        },
        {
          "name": "Smith",
          "option": "yes"
        },
        {
          "name": "Baker",
          "option": "yes"
        },
        {
          "name": "Dossett",
          "option": "yes"
        },
        {
          "name": "Hart",
          "option": "yes"
        },
        {
          "name": "McPherson",
          "option": "yes"
        },
        {
          "name": "Stalker",
          "option": "yes"
        },
        {
          "name": "Bauman",
          "option": "yes"
        },
        {
          "name": "Dotson",
          "option": "yes"
        },
        {
          "name": "Heavrin",
          "option": "yes"
        },
        {
          "name": "Meade",
          "option": "yes"
        },
        {
          "name": "Stevenson P",
          "option": "yes"
        },
        {
          "name": "Bivens",
          "option": "yes"
        },
        {
          "name": "Duvall",
          "option": "yes"
        },
        {
          "name": "Hodgson",
          "option": "yes"
        },
        {
          "name": "Meredith",
          "option": "yes"
        },
        {
          "name": "Tackett Laferty",
          "option": "yes"
        },
        {
          "name": "Blanton",
          "option": "yes"
        },
        {
          "name": "Elliott",
          "option": "yes"
        },
        {
          "name": "Huff T",
          "option": "yes"
        },
        {
          "name": "Miles",
          "option": "yes"
        },
        {
          "name": "Tate",
          "option": "yes"
        },
        {
          "name": "Bojanowski",
          "option": "yes"
        },
        {
          "name": "Fister",
          "option": "yes"
        },
        {
          "name": "Imes",
          "option": "yes"
        },
        {
          "name": "Moore",
          "option": "yes"
        },
        {
          "name": "Thomas",
          "option": "yes"
        },
        {
          "name": "Bowling",
          "option": "yes"
        },
        {
          "name": "Flannery",
          "option": "yes"
        },
        {
          "name": "Jackson",
          "option": "yes"
        },
        {
          "name": "Moser",
          "option": "yes"
        },
        {
          "name": "Thompson",
          "option": "yes"
        },
        {
          "name": "Branscum",
          "option": "yes"
        },
        {
          "name": "Fleming",
          "option": "yes"
        },
        {
          "name": "Johnson",
          "option": "yes"
        },
        {
          "name": "Neighbors",
          "option": "yes"
        },
        {
          "name": "Tipton",
          "option": "yes"
        },
        {
          "name": "Bratcher S.",
          "option": "yes"
        },
        {
          "name": "Freeland",
          "option": "yes"
        },
        {
          "name": "Koch",
          "option": "yes"
        },
        {
          "name": "Nemes",
          "option": "yes"
        },
        {
          "name": "Truett",
          "option": "yes"
        },
        {
          "name": "Bray",
          "option": "yes"
        },
        {
          "name": "Fugate",
          "option": "yes"
        },
        {
          "name": "Kulkarni",
          "option": "yes"
        },
        {
          "name": "Osborne",
          "option": "yes"
        },
        {
          "name": "Upchurch",
          "option": "yes"
        },
        {
          "name": "Bridges",
          "option": "yes"
        },
        {
          "name": "Gentry",
          "option": "yes"
        },
        {
          "name": "Lawrence",
          "option": "yes"
        },
        {
          "name": "Payne",
          "option": "yes"
        },
        {
          "name": "Watkins",
          "option": "yes"
        },
        {
          "name": "Brown",
          "option": "yes"
        },
        {
          "name": "Gordon",
          "option": "yes"
        },
        {
          "name": "Lehman",
          "option": "yes"
        },
        {
          "name": "Petrie",
          "option": "yes"
        },
        {
          "name": "Wesley",
          "option": "yes"
        },
        {
          "name": "Burke",
          "option": "yes"
        },
        {
          "name": "Griffee",
          "option": "yes"
        },
        {
          "name": "Lewis C",
          "option": "yes"
        },
        {
          "name": "Pollock",
          "option": "yes"
        },
        {
          "name": "Whitaker",
          "option": "yes"
        },
        {
          "name": "Camuel",
          "option": "yes"
        },
        {
          "name": "Grossberg",
          "option": "yes"
        },
        {
          "name": "Lewis D",
          "option": "yes"
        },
        {
          "name": "Raymer",
          "option": "yes"
        },
        {
          "name": "White",
          "option": "yes"
        },
        {
          "name": "Chester-Burton",
          "option": "yes"
        },
        {
          "name": "Grossl",
          "option": "yes"
        },
        {
          "name": "Lewis S",
          "option": "yes"
        },
        {
          "name": "Riley",
          "option": "yes"
        },
        {
          "name": "Williams",
          "option": "yes"
        },
        {
          "name": "Clines",
          "option": "yes"
        },
        {
          "name": "Hale",
          "option": "yes"
        },
        {
          "name": "Lockett",
          "option": "yes"
        },
        {
          "name": "Roarx",
          "option": "yes"
        },
        {
          "name": "Willner",
          "option": "yes"
        },
        {
          "name": "Decker",
          "option": "yes"
        },
        {
          "name": "Hampton",
          "option": "yes"
        },
        {
          "name": "Marzian",
          "option": "yes"
        },
        {
          "name": "Sharp",
          "option": "yes"
        },
        {
          "name": "Witten",
          "option": "yes"
        },
        {
          "name": "Dietz",
          "option": "yes"
        },
        {
          "name": "Banta",
          "option": "not voting"
        },
        {
          "name": "Doan",
          "option": "not voting"
        },
        {
          "name": "King",
          "option": "not voting"
        },
        {
          "name": "Proctor",
          "option": "not voting"
        },
        {
          "name": "Rudy",
          "option": "not voting"
        },
        {
          "name": "Callaway",
          "option": "not voting"
        },
        {
          "name": "Gooch",
          "option": "not voting"
        },
        {
          "name": "Maddox",
          "option": "not voting"
        },
        {
          "name": "Rabourn",
          "option": "not voting"
        },
        {
          "name": "Wilson",
          "option": "not voting"
        },
        {
          "name": "Calloway",
          "option": "not voting"
        },
        {
          "name": "Holloway",
          "option": "not voting"
        },
        {
          "name": "Massaroni",
          "option": "not voting"
        },
        {
          "name": "Roberts",
          "option": "not voting"
        }
      ]
    }
  ],
  "subjects": [
    "Children And Minors",
    "Education, Elementary And Secondary",
    "Education, Finance",
    "Health And Medical Services",
    "Medicaid",
    "Nurses",
    "State Agencies"
  ],
  "chamber_progress": {
    "lower": "passed",
    "upper": "in_committee",
    "governor": null
  },
  "current_status": "Passed House, in Senate committee",
  "last_action_date": "2026-03-25",
  "source_url": "",
  "openstates_id": "ocd-bill/272e2433-c3ec-4bde-8897-c082552f9f74"
}