{
  "id": "openstates-ky-2026RS-hb858",
  "body_ids": [
    "ky-house"
  ],
  "session": "2026RS",
  "identifier": "HB 858",
  "title": "AN ACT relating to criminal mediation.",
  "abstract": "Create a new section of KRS Chapter 455 to establish mediation in criminal cases; establish professional requirements for mediators and parameters for mediation.",
  "classification": [
    "bill"
  ],
  "sponsors": [
    {
      "name": "P. Flannery",
      "party": null,
      "district": "96",
      "primary": true
    }
  ],
  "actions": [
    {
      "date": "2026-03-03",
      "description": "introduced in House",
      "chamber": "lower",
      "classification": [
        "introduction"
      ]
    },
    {
      "date": "2026-03-03",
      "description": "to Committee on Committees (H)",
      "chamber": "lower",
      "classification": [
        "referral-committee"
      ]
    },
    {
      "date": "2026-03-10",
      "description": "to Judiciary (H)",
      "chamber": "lower",
      "classification": [
        "referral-committee"
      ]
    }
  ],
  "votes": [],
  "subjects": [
    "Attorneys",
    "Crimes And Punishments",
    "Criminal Procedure"
  ],
  "chamber_progress": {
    "lower": "in_committee",
    "upper": null,
    "governor": null
  },
  "current_status": "In House committee",
  "last_action_date": "2026-03-10",
  "source_url": "",
  "openstates_id": "ocd-bill/1ad13a8b-fb45-4d90-972b-19af2a8b3ad1"
}