{
  "id": "openstates-ky-2026RS-sb345",
  "body_ids": [
    "ky-senate"
  ],
  "session": "2026RS",
  "identifier": "SB 345",
  "title": "AN ACT relating to Medicaid waiver program coverage for community interveners.",
  "abstract": "Create a new section of KRS Chapter 205 to define \"community intervener\"; require the Michelle P. waiver program to cover community intervener services if approved by the federal Centers for Medicare and Medicaid Services; require the Department for Medicaid Services to promulgate administrative regulations; require the cabinet or the Department for Medicaid Services to seek federal approval if it is determined that such approval is necessary; provide authorization from the General Assembly to make changes in the Medicaid program as required under KRS 205.5372(1).",
  "classification": [
    "bill"
  ],
  "sponsors": [
    {
      "name": "J. Adams",
      "party": null,
      "district": "36",
      "primary": true
    },
    {
      "name": "D. Carroll",
      "party": null,
      "district": "2",
      "primary": true
    },
    {
      "name": "G. Neal",
      "party": null,
      "district": "33",
      "primary": true
    }
  ],
  "actions": [
    {
      "date": "2026-03-02",
      "description": "introduced in Senate",
      "chamber": "upper",
      "classification": [
        "introduction"
      ]
    },
    {
      "date": "2026-03-02",
      "description": "to Committee on Committees (S)",
      "chamber": "upper",
      "classification": [
        "referral-committee"
      ]
    }
  ],
  "votes": [],
  "subjects": [
    "Administrative Regulations And Proceedings",
    "Blind Or Deaf Persons",
    "Medicaid"
  ],
  "chamber_progress": {
    "lower": null,
    "upper": "in_committee",
    "governor": null
  },
  "current_status": "In Senate committee",
  "last_action_date": "2026-03-02",
  "source_url": "",
  "openstates_id": "ocd-bill/65b3b3c9-c443-45f4-9e2c-4bd27041ec83"
}