{
  "id": "primegov-louisvilleky-10039",
  "body_id": "public-works-committee",
  "title": "Public Works Committee - THIS MEETING HAS BEEN CANCELLED",
  "date": "2026-03-17",
  "time": "16:00",
  "source_type": "primegov",
  "source_url": "https://louisvilleky.primegov.com/public/Portal/Meeting?meetingTemplateId=10039",
  "source_meeting_id": "10039",
  "video_url": "https://louisvilleky.new.swagit.com/events/45613",
  "attachments": [
    {
      "sha256": "d7dba1a9dd552cfb9372222bbb6cbf046ebe7a866cbe93864db86aadd8a9394c",
      "url": "https://pgwest.blob.core.windows.net/louisvilleky/Meetings/10039/Agenda_2026031313254575.pdf?sv=2017-04-17&sr=b&sig=Sx7qzV5anq2vnNBzarmxs1w%2BJFmICkIVEMuFXo%2Bw3TM%3D&st=2026-05-02T05%3A47%3A50Z&se=2026-05-04T05%3A47%3A50Z&sp=r",
      "mime": "application/pdf",
      "template_name": "Agenda",
      "extracted_text_path": "data/attachments/d7dba1a9dd552cfb9372222bbb6cbf046ebe7a866cbe93864db86aadd8a9394c.txt"
    }
  ],
  "items": [
    {
      "item_number": "1",
      "file_number": "26-0101",
      "title": "PAVING PLAN UPDATE \u2013 TBD",
      "section": null
    }
  ]
}