{
  "id": "ky-derek-lewis",
  "source": "openstates",
  "source_id": "ocd-person/60ef609e-8aed-4698-a626-664f536a6122",
  "name": "Derek Lewis",
  "body_id": "ky-house",
  "chamber": "lower",
  "party": "Republican",
  "district": "90",
  "active": true,
  "photo_url": "https://legislature.ky.gov/Legislators%20Thumbnail%20Images/house90.jpg",
  "contact": {
    "addresses": [
      {
        "classification": "capitol-mail",
        "address": "Room Annex 416, 702 Capital Ave., Frankfort, KY 40601"
      }
    ],
    "phones": [
      {
        "classification": "capitol-mail",
        "voice": "502-564-8100"
      }
    ],
    "emails": [
      "derek.lewis@kylegislature.gov"
    ],
    "links": []
  },
  "sources": [
    "https://openstates.org/person/derek-lewis-2wuersLMLfsALWrxL5c8oc/"
  ]
}